app/benchmark.py
app/installation_test.py
app/readme_example.py
graphcutting/EvolutionPart.py
graphcutting/GirvanNewmanPart.py
graphcutting/Installation.py
graphcutting/LouvainPart.py
graphcutting/MetisPart.py
graphcutting/Node2VecPart.py
graphcutting/SpectralPart.py
graphcutting/StepWisePart.py
graphcutting/ZoltanPart.py
graphcutting/__init__.py
graphcutting/util.py
graphcutting-0.0.7.dist-info/LICENSE
graphcutting-0.0.7.dist-info/METADATA
graphcutting-0.0.7.dist-info/WHEEL
graphcutting-0.0.7.dist-info/top_level.txt
graphcutting-0.0.7.dist-info/RECORD
