Metadata-Version: 2.2
Name: graphcutting
Version: 0.0.7
Summary: A graph partitioning toolbox
Author: Pierrick Pochelu
Author-email: Pierrick Pochelu <pierrick.pochelu@gmail.com>
Classifier: Programming Language :: Python :: 3
Classifier: Operating System :: OS Independent
Classifier: License :: OSI Approved :: Apache Software License
Requires-Python: >=3.8
License-File: LICENSE
Provides-Extra: all
Requires-Dist: networkx; extra == "all"
Requires-Dist: python-igraph; extra == "all"
Requires-Dist: igraph; extra == "all"
Requires-Dist: node2vec; extra == "all"
Requires-Dist: scikit-learn; extra == "all"
Requires-Dist: python-louvain; extra == "all"
Requires-Dist: PyMetis; extra == "all"
Dynamic: author
